txtchat/__init__.py
txtchat/agent/__init__.py
txtchat/agent/__main__.py
txtchat/agent/base.py
txtchat/agent/factory.py
txtchat/agent/rocketchat.py
txtchat/pipeline/__init__.py
txtchat/pipeline/wikisearch.py
txtchat-0.3.0.dist-info/LICENSE
txtchat-0.3.0.dist-info/METADATA
txtchat-0.3.0.dist-info/WHEEL
txtchat-0.3.0.dist-info/top_level.txt
txtchat-0.3.0.dist-info/RECORD
