Metadata-Version: 2.1
Name: txtchat
Version: 0.3.0
Summary: Build autonomous agents, retrieval augmented generation (RAG) processes and language model powered chat applications 
Home-page: https://github.com/neuml/txtchat
Author: NeuML
License: Apache 2.0: http://www.apache.org/licenses/LICENSE-2.0
Project-URL: Documentation, https://github.com/neuml/txtchat
Project-URL: Issue Tracker, https://github.com/neuml/txtchat/issues
Project-URL: Source Code, https://github.com/neuml/txtchat
Keywords: search embedding machine-learning nlp
Classifier: License :: OSI Approved :: Apache Software License
Classifier: Operating System :: OS Independent
Classifier: Programming Language :: Python :: 3
Classifier: Topic :: Scientific/Engineering :: Artificial Intelligence
Classifier: Topic :: Software Development
Classifier: Topic :: Text Processing :: Indexing
Classifier: Topic :: Utilities
Requires-Python: >=3.10
License-File: LICENSE
Requires-Dist: huggingface-hub >=0.19.0
Requires-Dist: pyyaml >=5.3
Requires-Dist: rocketchat-async >=4.2.0
Requires-Dist: txtai >=8.5.0
